.gitignore
CHANGES.rst
MANIFEST.in
README.rst
README.txt
bootstrap.py
buildout-plone3.cfg
buildout-plone4.cfg
setup.py
collective/__init__.py
collective.contentrules.mailtorole.egg-info/PKG-INFO
collective.contentrules.mailtorole.egg-info/SOURCES.txt
collective.contentrules.mailtorole.egg-info/dependency_links.txt
collective.contentrules.mailtorole.egg-info/entry_points.txt
collective.contentrules.mailtorole.egg-info/namespace_packages.txt
collective.contentrules.mailtorole.egg-info/not-zip-safe
collective.contentrules.mailtorole.egg-info/requires.txt
collective.contentrules.mailtorole.egg-info/top_level.txt
collective/contentrules/__init__.py
collective/contentrules/mailtorole/TODO.txt
collective/contentrules/mailtorole/__init__.py
collective/contentrules/mailtorole/configure.zcml
collective/contentrules/mailtorole/rebuild_i18n.sh
collective/contentrules/mailtorole/actions/__init__.py
collective/contentrules/mailtorole/actions/configure.zcml
collective/contentrules/mailtorole/actions/mail.py
collective/contentrules/mailtorole/actions/vocabularies.py
collective/contentrules/mailtorole/locales/collective.contentrules.mailtorole.pot
collective/contentrules/mailtorole/locales/manual.pot
collective/contentrules/mailtorole/locales/fr/LC_MESSAGES/collective.contentrules.mailtorole.mo
collective/contentrules/mailtorole/locales/fr/LC_MESSAGES/collective.contentrules.mailtorole.po
collective/contentrules/mailtorole/locales/it/LC_MESSAGES/collective.contentrules.mailtorole.mo
collective/contentrules/mailtorole/locales/it/LC_MESSAGES/collective.contentrules.mailtorole.po
collective/contentrules/mailtorole/locales/nl/LC_MESSAGES/collective.contentrules.mailtorole.mo
collective/contentrules/mailtorole/locales/nl/LC_MESSAGES/collective.contentrules.mailtorole.po
collective/contentrules/mailtorole/tests/__init__.py
collective/contentrules/mailtorole/tests/test_action_mailtorole.py