Metadata-Version: 1.1
Name: collective.contentrules.mailtorole
Version: 1.7
Summary: Send e-mail to users having a role on the object
Home-page: http://plone.org/products/collective.contentrules.mailtorole
Author: Zest Software (Fred van Dijk)
Author-email: info@zestsoftware.nl
License: GPL
Keywords: plone contentrules action mail
Platform: UNKNOWN
Classifier: Framework :: Plone
Classifier: Framework :: Plone :: 3.2
Classifier: Framework :: Plone :: 3.3
Classifier: Framework :: Plone :: 4.0
Classifier: Framework :: Plone :: 4.1
Classifier: Framework :: Plone :: 4.2
Classifier: Programming Language :: Python
Classifier: Topic :: Software Development :: Libraries :: Python Modules
